{
  "web": {
    "frontend": ["React.js", "Next.js", "TypeScript", "Tailwind CSS", "Framer Motion"],
    "backend": ["Node.js", "Express", "PostgreSQL", "MongoDB", "GraphQL"],
    "tools": ["Git", "Docker", "Vercel", "AWS"]
  },
  "app": {
    "mobile": ["React Native"],
    "backend": ["Firebase", "Node.js", "Python"],
    "tools": ["Android Studio", "Figma"]
  },
  "software": {
    "languages": ["Go", "Rust", "C++", "Java"],
    "systems": ["Kubernetes", "Docker"],
    "tools": ["Git", "CI/CD", "Linux"]
  },
  "security": {
    "specialties": ["Penetration Testing", "Vulnerability Assessment", "Secure Coding"],
    "tools": ["Burp Suite", "Metasploit", "OWASP"],
    "certifications": ["CEH", "OSCP"]
  }
}
